bigdl/__init__.py
bigdl/friesian/__init__.py
bigdl/friesian/feature/__init__.py
bigdl/friesian/feature/table.py
bigdl/friesian/feature/utils.py
bigdl/friesian/models/__init__.py
bigdl/friesian/models/tfrs_model.py
bigdl/friesian/utils/__init__.py
bigdl/friesian/utils/safepickle.py
bigdl/share/friesian/lib/bigdl-friesian-spark_3.1.3-2.4.0-jar-with-dependencies.jar
bigdl_friesian_spark3-2.4.0.dist-info/METADATA
bigdl_friesian_spark3-2.4.0.dist-info/WHEEL
bigdl_friesian_spark3-2.4.0.dist-info/dependency_links.txt
bigdl_friesian_spark3-2.4.0.dist-info/top_level.txt
bigdl_friesian_spark3-2.4.0.dist-info/RECORD
